dateutil/__init__.py
dateutil/_common.py
dateutil/_version.py
dateutil/easter.py
dateutil/relativedelta.py
dateutil/rrule.py
dateutil/tzwin.py
dateutil/utils.py
dateutil/parser/__init__.py
dateutil/parser/_parser.py
dateutil/parser/isoparser.py
dateutil/tz/__init__.py
dateutil/tz/_common.py
dateutil/tz/_factories.py
dateutil/tz/tz.py
dateutil/tz/win.py
dateutil/zoneinfo/__init__.py
dateutil/zoneinfo/dateutil-zoneinfo.tar.gz
dateutil/zoneinfo/rebuild.py
python_dateutil-2.7.4.dist-info/LICENSE.txt
python_dateutil-2.7.4.dist-info/METADATA
python_dateutil-2.7.4.dist-info/RECORD
python_dateutil-2.7.4.dist-info/WHEEL
python_dateutil-2.7.4.dist-info/top_level.txt
python_dateutil-2.7.4.dist-info/zip-safe
