Metadata-Version: 2.1
Name: python-dateutil
Version: 2.7.4
Summary: Extensions to the standard Python datetime module
Home-page: https://dateutil.readthedocs.io
Author: Gustavo Niemeyer
Author-email: gustavo@niemeyer.net
Maintainer: Paul Ganssle
Maintainer-email: dateutil@python.org
License: Dual License
Platform: UNKNOWN
Classifier: Development Status :: 5 - Production/Stable
Classifier: Intended Audience :: Developers
Classifier: License :: OSI Approved :: BSD License
Classifier: License :: OSI Approved :: Apache Software License
Classifier: Programming Language :: Python
Classifier: Programming Language :: Python :: 2
Classifier: Programming Language :: Python :: 2.7
Classifier: Programming Language :: Python :: 3
Classifier: Programming Language :: Python :: 3.3
Classifier: Programming Language :: Python :: 3.4
Classifier: Programming Language :: Python :: 3.5
Classifier: Programming Language :: Python :: 3.6
Classifier: Programming Language :: Python :: 3.7
Classifier: Topic :: Software Development :: Libraries
Requires: six
Requires-Python: >=2.7, !=3.0.*, !=3.1.*, !=3.2.*
